dist
sohyloha
templates
venv
